loony
