Metadata-Version: 1.1
Name: loony
Version: 1.1.15
Summary: Script to search and connect to EC2 instances.
Home-page: http://loony.studyblue.com
Author: Fred Vassard
Author-email: fred@studyblue.com
License: Copyright (c) 2012, Fred Vassard
